[
    {
        "id": "escudo-radiador",
        "nome": "Escudo Radiador",
        "descricoes": [
            "Um escudo médio de metal, relativamente fácil de manejar.",
            "Escudos de metal são confiáveis, negando o dano físico recebido ao defender, uma característica que os tornou muito confiáveis no campo de batalha."
        ],
        "tipo": {
            "id": "escudo-medio",
            "nome": "Escudo Médio"
        },
        "subTipo": {
            "id": "esmagador",
            "nome": "Esmagador"
        },
        "imagens": {
            "icone": "https://github.com/inaciofabricio/anotacoes/blob/main/elder-ring/image/armas/escudos/escudo-radiador-icone.jpg?raw=true",
            "padrao": "https://github.com/inaciofabricio/anotacoes/blob/main/elder-ring/image/armas/escudos/escudo-radiador-padrao.jpg?raw=true"
        },
        "poderDeAtaque" :{
            "fisico": 77,
            "magico": 0,
            "fogo": 0,
            "relampago": 0,
            "sagrado": 0,
            "critico": 100
        },
        "danoNegadoAoDefender": {
            "fisico": 100.0,
            "magico": 43.0,
            "fogo": 43.0,
            "relampago": 27.0,
            "sagrado": 43.0,
            "aumentoDeDefesa": 49
        },
        "bonusDeAtributo" : {
            "for": "D",
            "des": "-",
            "int": "-",
            "fe": "-",
            "arc": "-"
        },
        "atributosNecessarios" : {
            "for": 10,
            "des": 0,
            "int": 0,
            "fe": 0,
            "arc": 0
        },
        "efeitosPassivos": [],
        "habilidade": {
            "id": "aparagem",
            "nome": "Aparagem",
            "descricoes": [
                "Sincronize esta habilidade com o ataque inimigo para desviá-lo e quebrar a postura do adversário.",
                "Isso cria uma abertura para executar um ataque crítico."
            ]
        }
    },
    {
        "id": "escudo-de-madeira-reforcado",
        "nome": "Escudo de Madeira Reforçado",
        "descricoes": [
            "Pequeno escudo redondo de mardeira reforçado com metal. Leve e fácil de manusear, mas não oferece a mesma negação de dado que um escudo de metal de verdade.",
            "O desenho rebitado ao centro represanta tanto a espada quanto a árvore."
        ],
        "tipo": {
            "id": "escudo-pequeno",
            "nome": "Escudo Pequeno"
        },
        "subTipo": {
            "id": "esmagador",
            "nome": "Esmagador"
        },
        "imagens": {
            "icone": "https://github.com/inaciofabricio/anotacoes/blob/main/elder-ring/image/armas/escudos/escudo-de-madeira-reforcado-icone.jpg?raw=true",
            "padrao": "https://github.com/inaciofabricio/anotacoes/blob/main/elder-ring/image/armas/escudos/escudo-de-madeira-reforcado-padrao.jpg?raw=true"
        },
        "poderDeAtaque" :{
            "fisico": 72,
            "magico": 0,
            "fogo": 0,
            "relampago": 0,
            "sagrado": 0,
            "critico": 100
        },
        "danoNegadoAoDefender": {
            "fisico": 74.0,
            "magico": 43.0,
            "fogo": 31.0,
            "relampago": 24.0,
            "sagrado": 45.0,
            "aumentoDeDefesa": 39
        },
        "bonusDeAtributo" : {
            "for": "E",
            "des": "-",
            "int": "-",
            "fe": "-",
            "arc": "-"
        },
        "atributosNecessarios" : {
            "for": 8,
            "des": 0,
            "int": 0,
            "fe": 0,
            "arc": 0
        },
        "efeitosPassivos": [],
        "habilidade": {
            "id": "aparagem",
            "nome": "Aparagem",
            "descricoes": [
                "Sincronize esta habilidade com o ataque inimigo para desviá-lo e quebrar a postura do adversário.",
                "Isso cria uma abertura para executar um ataque crítico."
            ]
        }
    }
]